[
  {
    "name": "0x-api",
    "link": "0x-api.html"
  },
  {
    "name": "1inch",
    "link": "1inch.html"
  },
  {
    "name": "3box-labs",
    "link": "3box-labs.html"
  },
  {
    "name": "51-attack",
    "link": "51-attack.html"
  },
  {
    "name": "aave",
    "link": "aave.html"
  },
  {
    "name": "about",
    "link": "about.html"
  },
  {
    "name": "account",
    "link": "account.html"
  },
  {
    "name": "ach-transfer",
    "link": "ach-transfer.html"
  },
  {
    "name": "address",
    "link": "address.html"
  },
  {
    "name": "advanced",
    "link": "advanced.html"
  },
  {
    "name": "aggregator",
    "link": "aggregator.html"
  },
  {
    "name": "aggressive",
    "link": "aggressive.html"
  },
  {
    "name": "agoric",
    "link": "agoric.html"
  },
  {
    "name": "air-gapping",
    "link": "air-gapping.html"
  },
  {
    "name": "airdrop",
    "link": "airdrop.html"
  },
  {
    "name": "airgap-vault",
    "link": "airgap-vault.html"
  },
  {
    "name": "airswap",
    "link": "airswap.html"
  },
  {
    "name": "alerts",
    "link": "alerts.html"
  },
  {
    "name": "algorithm",
    "link": "algorithm.html"
  },
  {
    "name": "altcoin",
    "link": "altcoin.html"
  },
  {
    "name": "aml-(anti-money-laundering)",
    "link": "aml-(anti-money-laundering).html"
  },
  {
    "name": "api-(application-programming-interface)",
    "link": "api-(application-programming-interface).html"
  },
  {
    "name": "api",
    "link": "api.html"
  },
  {
    "name": "appchain",
    "link": "appchain.html"
  },
  {
    "name": "apple-pay",
    "link": "apple-pay.html"
  },
  {
    "name": "approve",
    "link": "approve.html"
  },
  {
    "name": "arbitrum",
    "link": "arbitrum.html"
  },
  {
    "name": "asic-(application-specific-integrated-circuit)",
    "link": "asic-(application-specific-integrated-circuit).html"
  },
  {
    "name": "asset-provenance",
    "link": "asset-provenance.html"
  },
  {
    "name": "attestation",
    "link": "attestation.html"
  },
  {
    "name": "aurora",
    "link": "aurora.html"
  },
  {
    "name": "autodetection",
    "link": "autodetection.html"
  },
  {
    "name": "avalanche",
    "link": "avalanche.html"
  },
  {
    "name": "avax",
    "link": "avax.html"
  },
  {
    "name": "axie-infinity",
    "link": "axie-infinity.html"
  },
  {
    "name": "backup",
    "link": "backup.html"
  },
  {
    "name": "balance",
    "link": "balance.html"
  },
  {
    "name": "banxa",
    "link": "banxa.html"
  },
  {
    "name": "base-fee",
    "link": "base-fee.html"
  },
  {
    "name": "beacon-chain",
    "link": "beacon-chain.html"
  },
  {
    "name": "besu",
    "link": "besu.html"
  },
  {
    "name": "binance",
    "link": "binance.html"
  },
  {
    "name": "biometrics",
    "link": "biometrics.html"
  },
  {
    "name": "bitcoin",
    "link": "bitcoin.html"
  },
  {
    "name": "block-(noun)",
    "link": "block-(noun).html"
  },
  {
    "name": "block-explorer",
    "link": "block-explorer.html"
  },
  {
    "name": "block-height",
    "link": "block-height.html"
  },
  {
    "name": "block-reward",
    "link": "block-reward.html"
  },
  {
    "name": "block-time",
    "link": "block-time.html"
  },
  {
    "name": "blockchain-explorer",
    "link": "blockchain-explorer.html"
  },
  {
    "name": "blockchain-trilemma",
    "link": "blockchain-trilemma.html"
  },
  {
    "name": "blockchain",
    "link": "blockchain.html"
  },
  {
    "name": "blockies",
    "link": "blockies.html"
  },
  {
    "name": "bnb-chain",
    "link": "bnb-chain.html"
  },
  {
    "name": "bnb",
    "link": "bnb.html"
  },
  {
    "name": "bounty--bug-bounty",
    "link": "bounty--bug-bounty.html"
  },
  {
    "name": "brain-wallet",
    "link": "brain-wallet.html"
  },
  {
    "name": "brave",
    "link": "brave.html"
  },
  {
    "name": "bridge",
    "link": "bridge.html"
  },
  {
    "name": "browser",
    "link": "browser.html"
  },
  {
    "name": "btc",
    "link": "btc.html"
  },
  {
    "name": "bug-report",
    "link": "bug-report.html"
  },
  {
    "name": "buidl",
    "link": "buidl.html"
  },
  {
    "name": "bytecode",
    "link": "bytecode.html"
  },
  {
    "name": "byzantine-fault-tolerance",
    "link": "byzantine-fault-tolerance.html"
  },
  {
    "name": "byzantium-fork",
    "link": "byzantium-fork.html"
  },
  {
    "name": "cancel",
    "link": "cancel.html"
  },
  {
    "name": "celo",
    "link": "celo.html"
  },
  {
    "name": "centralized-exchange-(cex)",
    "link": "centralized-exchange-(cex).html"
  },
  {
    "name": "centralized-exchange",
    "link": "centralized-exchange.html"
  },
  {
    "name": "cex",
    "link": "cex.html"
  },
  {
    "name": "chain-id",
    "link": "chain-id.html"
  },
  {
    "name": "chrome",
    "link": "chrome.html"
  },
  {
    "name": "clear",
    "link": "clear.html"
  },
  {
    "name": "client-(ethereum-or-other-compatible-blockchain)",
    "link": "client-(ethereum-or-other-compatible-blockchain).html"
  },
  {
    "name": "codefi",
    "link": "codefi.html"
  },
  {
    "name": "coinbase-pay",
    "link": "coinbase-pay.html"
  },
  {
    "name": "coingecko",
    "link": "coingecko.html"
  },
  {
    "name": "cold-storage",
    "link": "cold-storage.html"
  },
  {
    "name": "cold-wallet--cold-storage",
    "link": "cold-wallet--cold-storage.html"
  },
  {
    "name": "community-platform",
    "link": "community-platform.html"
  },
  {
    "name": "compiling",
    "link": "compiling.html"
  },
  {
    "name": "compound",
    "link": "compound.html"
  },
  {
    "name": "confirm",
    "link": "confirm.html"
  },
  {
    "name": "confirmation",
    "link": "confirmation.html"
  },
  {
    "name": "consensus-client",
    "link": "consensus-client.html"
  },
  {
    "name": "consensus-layer",
    "link": "consensus-layer.html"
  },
  {
    "name": "consensus-mechanism",
    "link": "consensus-mechanism.html"
  },
  {
    "name": "consensus",
    "link": "consensus.html"
  },
  {
    "name": "consensys",
    "link": "consensys.html"
  },
  {
    "name": "constantinople-fork",
    "link": "constantinople-fork.html"
  },
  {
    "name": "contacts",
    "link": "contacts.html"
  },
  {
    "name": "contract-account",
    "link": "contract-account.html"
  },
  {
    "name": "contract",
    "link": "contract.html"
  },
  {
    "name": "conversion",
    "link": "conversion.html"
  },
  {
    "name": "coolwallet",
    "link": "coolwallet.html"
  },
  {
    "name": "copy",
    "link": "copy.html"
  },
  {
    "name": "create",
    "link": "create.html"
  },
  {
    "name": "crypto-",
    "link": "crypto-.html"
  },
  {
    "name": "crypto-asset",
    "link": "crypto-asset.html"
  },
  {
    "name": "crypto-bounties",
    "link": "crypto-bounties.html"
  },
  {
    "name": "crypto-compliance",
    "link": "crypto-compliance.html"
  },
  {
    "name": "crypto-fund",
    "link": "crypto-fund.html"
  },
  {
    "name": "crypto-wallet",
    "link": "crypto-wallet.html"
  },
  {
    "name": "cryptoassets",
    "link": "cryptoassets.html"
  },
  {
    "name": "cryptocompare",
    "link": "cryptocompare.html"
  },
  {
    "name": "cryptocurrency",
    "link": "cryptocurrency.html"
  },
  {
    "name": "cryptoeconomics",
    "link": "cryptoeconomics.html"
  },
  {
    "name": "cryptography",
    "link": "cryptography.html"
  },
  {
    "name": "curve",
    "link": "curve.html"
  },
  {
    "name": "custody-(noun)",
    "link": "custody-(noun).html"
  },
  {
    "name": "custom-nonce",
    "link": "custom-nonce.html"
  },
  {
    "name": "d'cent",
    "link": "d'cent.html"
  },
  {
    "name": "dai",
    "link": "dai.html"
  },
  {
    "name": "dao",
    "link": "dao.html"
  },
  {
    "name": "dapp",
    "link": "dapp.html"
  },
  {
    "name": "decentralization",
    "link": "decentralization.html"
  },
  {
    "name": "decentralized-application",
    "link": "decentralized-application.html"
  },
  {
    "name": "decentralized-autonomous-organization-(dao)",
    "link": "decentralized-autonomous-organization-(dao).html"
  },
  {
    "name": "decentralized-autonomous-organization",
    "link": "decentralized-autonomous-organization.html"
  },
  {
    "name": "decentralized-exchange-(dex)",
    "link": "decentralized-exchange-(dex).html"
  },
  {
    "name": "decentralized-exchange",
    "link": "decentralized-exchange.html"
  },
  {
    "name": "decentralized-finance",
    "link": "decentralized-finance.html"
  },
  {
    "name": "decentralized-web",
    "link": "decentralized-web.html"
  },
  {
    "name": "default",
    "link": "default.html"
  },
  {
    "name": "defi",
    "link": "defi.html"
  },
  {
    "name": "delegated-proof-of-stake-(dpos)",
    "link": "delegated-proof-of-stake-(dpos).html"
  },
  {
    "name": "delete",
    "link": "delete.html"
  },
  {
    "name": "deposit",
    "link": "deposit.html"
  },
  {
    "name": "derive--derivation",
    "link": "derive--derivation.html"
  },
  {
    "name": "dev",
    "link": "dev.html"
  },
  {
    "name": "devcon",
    "link": "devcon.html"
  },
  {
    "name": "developer",
    "link": "developer.html"
  },
  {
    "name": "device",
    "link": "device.html"
  },
  {
    "name": "dex",
    "link": "dex.html"
  },
  {
    "name": "difficulty-bomb",
    "link": "difficulty-bomb.html"
  },
  {
    "name": "difficulty",
    "link": "difficulty.html"
  },
  {
    "name": "digital-asset",
    "link": "digital-asset.html"
  },
  {
    "name": "digital-identity",
    "link": "digital-identity.html"
  },
  {
    "name": "digital-signature",
    "link": "digital-signature.html"
  },
  {
    "name": "diligence",
    "link": "diligence.html"
  },
  {
    "name": "disable",
    "link": "disable.html"
  },
  {
    "name": "distributed-denial-of-service-(ddos)-attack",
    "link": "distributed-denial-of-service-(ddos)-attack.html"
  },
  {
    "name": "distributed-ledger-technology",
    "link": "distributed-ledger-technology.html"
  },
  {
    "name": "distributed-ledger",
    "link": "distributed-ledger.html"
  },
  {
    "name": "dlt",
    "link": "dlt.html"
  },
  {
    "name": "double-spend",
    "link": "double-spend.html"
  },
  {
    "name": "download",
    "link": "download.html"
  },
  {
    "name": "dropped",
    "link": "dropped.html"
  },
  {
    "name": "ecosystem",
    "link": "ecosystem.html"
  },
  {
    "name": "edge",
    "link": "edge.html"
  },
  {
    "name": "edit",
    "link": "edit.html"
  },
  {
    "name": "eip-1559",
    "link": "eip-1559.html"
  },
  {
    "name": "enable",
    "link": "enable.html"
  },
  {
    "name": "encrypted-vs-unencrypted-keys",
    "link": "encrypted-vs-unencrypted-keys.html"
  },
  {
    "name": "encryption",
    "link": "encryption.html"
  },
  {
    "name": "ens",
    "link": "ens.html"
  },
  {
    "name": "enterprise-ethereum-alliance-(eea)",
    "link": "enterprise-ethereum-alliance-(eea).html"
  },
  {
    "name": "entropy",
    "link": "entropy.html"
  },
  {
    "name": "epoch",
    "link": "epoch.html"
  },
  {
    "name": "erc-1155",
    "link": "erc-1155.html"
  },
  {
    "name": "erc-20-token-standard",
    "link": "erc-20-token-standard.html"
  },
  {
    "name": "erc-20",
    "link": "erc-20.html"
  },
  {
    "name": "erc-721-token-standard",
    "link": "erc-721-token-standard.html"
  },
  {
    "name": "erc-721",
    "link": "erc-721.html"
  },
  {
    "name": "erc",
    "link": "erc.html"
  },
  {
    "name": "error",
    "link": "error.html"
  },
  {
    "name": "eth",
    "link": "eth.html"
  },
  {
    "name": "ether-(denominations)",
    "link": "ether-(denominations).html"
  },
  {
    "name": "ether-(eth)",
    "link": "ether-(eth).html"
  },
  {
    "name": "ether",
    "link": "ether.html"
  },
  {
    "name": "ethereum-2.0",
    "link": "ethereum-2.0.html"
  },
  {
    "name": "ethereum-improvement-proposal-(eip)",
    "link": "ethereum-improvement-proposal-(eip).html"
  },
  {
    "name": "ethereum-improvement-protocols",
    "link": "ethereum-improvement-protocols.html"
  },
  {
    "name": "ethereum-mainnet",
    "link": "ethereum-mainnet.html"
  },
  {
    "name": "ethereum-name-service-(ens)",
    "link": "ethereum-name-service-(ens).html"
  },
  {
    "name": "ethereum-name-service",
    "link": "ethereum-name-service.html"
  },
  {
    "name": "ethereum-public-address",
    "link": "ethereum-public-address.html"
  },
  {
    "name": "ethereum-virtual-machine-(evm)",
    "link": "ethereum-virtual-machine-(evm).html"
  },
  {
    "name": "ethereum-virtual-machine",
    "link": "ethereum-virtual-machine.html"
  },
  {
    "name": "ethereum",
    "link": "ethereum.html"
  },
  {
    "name": "etherscan",
    "link": "etherscan.html"
  },
  {
    "name": "eur",
    "link": "eur.html"
  },
  {
    "name": "evm",
    "link": "evm.html"
  },
  {
    "name": "exchange",
    "link": "exchange.html"
  },
  {
    "name": "execution-client",
    "link": "execution-client.html"
  },
  {
    "name": "execution-layer",
    "link": "execution-layer.html"
  },
  {
    "name": "experimental",
    "link": "experimental.html"
  },
  {
    "name": "export",
    "link": "export.html"
  },
  {
    "name": "extended-private-key-(xpriv)",
    "link": "extended-private-key-(xpriv).html"
  },
  {
    "name": "extended-public-key-(xpub)",
    "link": "extended-public-key-(xpub).html"
  },
  {
    "name": "extension",
    "link": "extension.html"
  },
  {
    "name": "failed",
    "link": "failed.html"
  },
  {
    "name": "fantom",
    "link": "fantom.html"
  },
  {
    "name": "faucet",
    "link": "faucet.html"
  },
  {
    "name": "fiat-currency",
    "link": "fiat-currency.html"
  },
  {
    "name": "final,-finality",
    "link": "final,-finality.html"
  },
  {
    "name": "finality-rate",
    "link": "finality-rate.html"
  },
  {
    "name": "financial-technology",
    "link": "financial-technology.html"
  },
  {
    "name": "finney",
    "link": "finney.html"
  },
  {
    "name": "fintech",
    "link": "fintech.html"
  },
  {
    "name": "firefox",
    "link": "firefox.html"
  },
  {
    "name": "firewall",
    "link": "firewall.html"
  },
  {
    "name": "firmware",
    "link": "firmware.html"
  },
  {
    "name": "flask-(metamask-flask)",
    "link": "flask-(metamask-flask).html"
  },
  {
    "name": "flask",
    "link": "flask.html"
  },
  {
    "name": "fork",
    "link": "fork.html"
  },
  {
    "name": "fractional-ownership",
    "link": "fractional-ownership.html"
  },
  {
    "name": "fraud-proof",
    "link": "fraud-proof.html"
  },
  {
    "name": "ftm",
    "link": "ftm.html"
  },
  {
    "name": "full-node",
    "link": "full-node.html"
  },
  {
    "name": "ganache",
    "link": "ganache.html"
  },
  {
    "name": "gas-fee",
    "link": "gas-fee.html"
  },
  {
    "name": "gas-limit",
    "link": "gas-limit.html"
  },
  {
    "name": "gas-price",
    "link": "gas-price.html"
  },
  {
    "name": "gas-station-network",
    "link": "gas-station-network.html"
  },
  {
    "name": "gas",
    "link": "gas.html"
  },
  {
    "name": "gbp",
    "link": "gbp.html"
  },
  {
    "name": "general",
    "link": "general.html"
  },
  {
    "name": "genesis-block",
    "link": "genesis-block.html"
  },
  {
    "name": "gigawei",
    "link": "gigawei.html"
  },
  {
    "name": "gitcoin",
    "link": "gitcoin.html"
  },
  {
    "name": "github",
    "link": "github.html"
  },
  {
    "name": "goerli",
    "link": "goerli.html"
  },
  {
    "name": "governance",
    "link": "governance.html"
  },
  {
    "name": "gsn",
    "link": "gsn.html"
  },
  {
    "name": "gwei",
    "link": "gwei.html"
  },
  {
    "name": "halving",
    "link": "halving.html"
  },
  {
    "name": "hard-fork",
    "link": "hard-fork.html"
  },
  {
    "name": "hardware-wallet",
    "link": "hardware-wallet.html"
  },
  {
    "name": "harmony",
    "link": "harmony.html"
  },
  {
    "name": "hash-(noun)",
    "link": "hash-(noun).html"
  },
  {
    "name": "hex-data",
    "link": "hex-data.html"
  },
  {
    "name": "hexadecimal-'hex-data'",
    "link": "hexadecimal-'hex-data'.html"
  },
  {
    "name": "hide",
    "link": "hide.html"
  },
  {
    "name": "hierarchical-deterministic-(hd)-wallet",
    "link": "hierarchical-deterministic-(hd)-wallet.html"
  },
  {
    "name": "hot-storage",
    "link": "hot-storage.html"
  },
  {
    "name": "hot-wallet",
    "link": "hot-wallet.html"
  },
  {
    "name": "hybrid-network",
    "link": "hybrid-network.html"
  },
  {
    "name": "hyperledger",
    "link": "hyperledger.html"
  },
  {
    "name": "ico",
    "link": "ico.html"
  },
  {
    "name": "id",
    "link": "id.html"
  },
  {
    "name": "identicon",
    "link": "identicon.html"
  },
  {
    "name": "immutability",
    "link": "immutability.html"
  },
  {
    "name": "import",
    "link": "import.html"
  },
  {
    "name": "infura",
    "link": "infura.html"
  },
  {
    "name": "initial-public-offering-(ipo)",
    "link": "initial-public-offering-(ipo).html"
  },
  {
    "name": "insider-trading",
    "link": "insider-trading.html"
  },
  {
    "name": "install",
    "link": "install.html"
  },
  {
    "name": "institutional-(metamask-institutional)-(mmi)",
    "link": "institutional-(metamask-institutional)-(mmi).html"
  },
  {
    "name": "institutional",
    "link": "institutional.html"
  },
  {
    "name": "inter-blockchain-communication-(ibc)-protocol",
    "link": "inter-blockchain-communication-(ibc)-protocol.html"
  },
  {
    "name": "internal-transaction",
    "link": "internal-transaction.html"
  },
  {
    "name": "interoperability",
    "link": "interoperability.html"
  },
  {
    "name": "interplanetary-file-system-(ipfs)",
    "link": "interplanetary-file-system-(ipfs).html"
  },
  {
    "name": "invalid",
    "link": "invalid.html"
  },
  {
    "name": "ip-address",
    "link": "ip-address.html"
  },
  {
    "name": "ipfs",
    "link": "ipfs.html"
  },
  {
    "name": "jazzicons",
    "link": "jazzicons.html"
  },
  {
    "name": "json-file",
    "link": "json-file.html"
  },
  {
    "name": "json-rpc",
    "link": "json-rpc.html"
  },
  {
    "name": "keystore-file",
    "link": "keystore-file.html"
  },
  {
    "name": "know-your-customer-(kyc)",
    "link": "know-your-customer-(kyc).html"
  },
  {
    "name": "know-your-customer",
    "link": "know-your-customer.html"
  },
  {
    "name": "know-your-transaction",
    "link": "know-your-transaction.html"
  },
  {
    "name": "kovan",
    "link": "kovan.html"
  },
  {
    "name": "kyc",
    "link": "kyc.html"
  },
  {
    "name": "kyt",
    "link": "kyt.html"
  },
  {
    "name": "latency",
    "link": "latency.html"
  },
  {
    "name": "lattice1",
    "link": "lattice1.html"
  },
  {
    "name": "launchpad",
    "link": "launchpad.html"
  },
  {
    "name": "layer-0",
    "link": "layer-0.html"
  },
  {
    "name": "layer-1",
    "link": "layer-1.html"
  },
  {
    "name": "layer-2",
    "link": "layer-2.html"
  },
  {
    "name": "learn-metamask-learn",
    "link": "learn-metamask-learn.html"
  },
  {
    "name": "learn",
    "link": "learn.html"
  },
  {
    "name": "ledger-live-app",
    "link": "ledger-live-app.html"
  },
  {
    "name": "ledger-live",
    "link": "ledger-live.html"
  },
  {
    "name": "ledger",
    "link": "ledger.html"
  },
  {
    "name": "library",
    "link": "library.html"
  },
  {
    "name": "lido",
    "link": "lido.html"
  },
  {
    "name": "light-client",
    "link": "light-client.html"
  },
  {
    "name": "lightning-network",
    "link": "lightning-network.html"
  },
  {
    "name": "linea",
    "link": "linea.html"
  },
  {
    "name": "link",
    "link": "link.html"
  },
  {
    "name": "liquid-democracy-(delegative-democracy)",
    "link": "liquid-democracy-(delegative-democracy).html"
  },
  {
    "name": "liquidation",
    "link": "liquidation.html"
  },
  {
    "name": "liquidity-pool",
    "link": "liquidity-pool.html"
  },
  {
    "name": "liquidity-staking",
    "link": "liquidity-staking.html"
  },
  {
    "name": "liquidity",
    "link": "liquidity.html"
  },
  {
    "name": "lock",
    "link": "lock.html"
  },
  {
    "name": "low",
    "link": "low.html"
  },
  {
    "name": "maker-protocol",
    "link": "maker-protocol.html"
  },
  {
    "name": "malware",
    "link": "malware.html"
  },
  {
    "name": "market-cap",
    "link": "market-cap.html"
  },
  {
    "name": "matic",
    "link": "matic.html"
  },
  {
    "name": "maximal-extractable-value-(mev)",
    "link": "maximal-extractable-value-(mev).html"
  },
  {
    "name": "maximum-priority-fee",
    "link": "maximum-priority-fee.html"
  },
  {
    "name": "memory-pool-mempool",
    "link": "memory-pool-mempool.html"
  },
  {
    "name": "mempool",
    "link": "mempool.html"
  },
  {
    "name": "mercuryo",
    "link": "mercuryo.html"
  },
  {
    "name": "merge-(noun)",
    "link": "merge-(noun).html"
  },
  {
    "name": "merkle-patricia-trie",
    "link": "merkle-patricia-trie.html"
  },
  {
    "name": "mesh",
    "link": "mesh.html"
  },
  {
    "name": "metadata",
    "link": "metadata.html"
  },
  {
    "name": "metamask-bridge",
    "link": "metamask-bridge.html"
  },
  {
    "name": "metamask-community-platform",
    "link": "metamask-community-platform.html"
  },
  {
    "name": "metamask-extension",
    "link": "metamask-extension.html"
  },
  {
    "name": "metamask-flask",
    "link": "metamask-flask.html"
  },
  {
    "name": "metamask-institutional",
    "link": "metamask-institutional.html"
  },
  {
    "name": "metamask-learn",
    "link": "metamask-learn.html"
  },
  {
    "name": "metamask-sdk",
    "link": "metamask-sdk.html"
  },
  {
    "name": "metamask-support",
    "link": "metamask-support.html"
  },
  {
    "name": "metamask-swaps",
    "link": "metamask-swaps.html"
  },
  {
    "name": "metamask",
    "link": "metamask.html"
  },
  {
    "name": "metametrics",
    "link": "metametrics.html"
  },
  {
    "name": "metaverse",
    "link": "metaverse.html"
  },
  {
    "name": "miner-tip",
    "link": "miner-tip.html"
  },
  {
    "name": "miner",
    "link": "miner.html"
  },
  {
    "name": "mining",
    "link": "mining.html"
  },
  {
    "name": "mint",
    "link": "mint.html"
  },
  {
    "name": "mnemonic-phrase",
    "link": "mnemonic-phrase.html"
  },
  {
    "name": "mobikwik",
    "link": "mobikwik.html"
  },
  {
    "name": "modular-blockchain",
    "link": "modular-blockchain.html"
  },
  {
    "name": "moonpay",
    "link": "moonpay.html"
  },
  {
    "name": "multi-sig",
    "link": "multi-sig.html"
  },
  {
    "name": "multi-signature-wallet-(multisig)",
    "link": "multi-signature-wallet-(multisig).html"
  },
  {
    "name": "multifactor-authentication",
    "link": "multifactor-authentication.html"
  },
  {
    "name": "near-field-communication-(nfc)",
    "link": "near-field-communication-(nfc).html"
  },
  {
    "name": "nested-blockchain",
    "link": "nested-blockchain.html"
  },
  {
    "name": "network-congestion",
    "link": "network-congestion.html"
  },
  {
    "name": "network",
    "link": "network.html"
  },
  {
    "name": "nft-aggregator",
    "link": "nft-aggregator.html"
  },
  {
    "name": "nft-drop",
    "link": "nft-drop.html"
  },
  {
    "name": "nft",
    "link": "nft.html"
  },
  {
    "name": "ngrave",
    "link": "ngrave.html"
  },
  {
    "name": "node",
    "link": "node.html"
  },
  {
    "name": "non-fungible-token",
    "link": "non-fungible-token.html"
  },
  {
    "name": "nonce",
    "link": "nonce.html"
  },
  {
    "name": "off-chain",
    "link": "off-chain.html"
  },
  {
    "name": "ommer-block",
    "link": "ommer-block.html"
  },
  {
    "name": "on-chain",
    "link": "on-chain.html"
  },
  {
    "name": "on-ramp,-off-ramp",
    "link": "on-ramp,-off-ramp.html"
  },
  {
    "name": "on-ramp",
    "link": "on-ramp.html"
  },
  {
    "name": "one",
    "link": "one.html"
  },
  {
    "name": "opensea",
    "link": "opensea.html"
  },
  {
    "name": "opera",
    "link": "opera.html"
  },
  {
    "name": "optimism",
    "link": "optimism.html"
  },
  {
    "name": "optimistic-rollup",
    "link": "optimistic-rollup.html"
  },
  {
    "name": "optional",
    "link": "optional.html"
  },
  {
    "name": "oracle",
    "link": "oracle.html"
  },
  {
    "name": "p2p",
    "link": "p2p.html"
  },
  {
    "name": "palm",
    "link": "palm.html"
  },
  {
    "name": "paraswap",
    "link": "paraswap.html"
  },
  {
    "name": "parity",
    "link": "parity.html"
  },
  {
    "name": "passphrase",
    "link": "passphrase.html"
  },
  {
    "name": "password-manager",
    "link": "password-manager.html"
  },
  {
    "name": "password",
    "link": "password.html"
  },
  {
    "name": "paypal",
    "link": "paypal.html"
  },
  {
    "name": "peer-to-peer-(p2p)",
    "link": "peer-to-peer-(p2p).html"
  },
  {
    "name": "peer-to-peer",
    "link": "peer-to-peer.html"
  },
  {
    "name": "pending",
    "link": "pending.html"
  },
  {
    "name": "permission",
    "link": "permission.html"
  },
  {
    "name": "permissioned-ledger",
    "link": "permissioned-ledger.html"
  },
  {
    "name": "phishing-(noun)",
    "link": "phishing-(noun).html"
  },
  {
    "name": "plasma",
    "link": "plasma.html"
  },
  {
    "name": "poa,-pos,-pow",
    "link": "poa,-pos,-pow.html"
  },
  {
    "name": "polygon",
    "link": "polygon.html"
  },
  {
    "name": "portfolio",
    "link": "portfolio.html"
  },
  {
    "name": "pospow-hybrid",
    "link": "pospow-hybrid.html"
  },
  {
    "name": "priority-fee",
    "link": "priority-fee.html"
  },
  {
    "name": "private-blockchain",
    "link": "private-blockchain.html"
  },
  {
    "name": "private-currency",
    "link": "private-currency.html"
  },
  {
    "name": "private-key",
    "link": "private-key.html"
  },
  {
    "name": "proof-of-authority-(poa)",
    "link": "proof-of-authority-(poa).html"
  },
  {
    "name": "proof-of-stake-(pos)",
    "link": "proof-of-stake-(pos).html"
  },
  {
    "name": "proof-of-stake",
    "link": "proof-of-stake.html"
  },
  {
    "name": "proof-of-work-(pow)",
    "link": "proof-of-work-(pow).html"
  },
  {
    "name": "proof-of-work",
    "link": "proof-of-work.html"
  },
  {
    "name": "protocol",
    "link": "protocol.html"
  },
  {
    "name": "public-address",
    "link": "public-address.html"
  },
  {
    "name": "public-blockchain",
    "link": "public-blockchain.html"
  },
  {
    "name": "public-key-cryptography",
    "link": "public-key-cryptography.html"
  },
  {
    "name": "public-key-infrastructure",
    "link": "public-key-infrastructure.html"
  },
  {
    "name": "public-key",
    "link": "public-key.html"
  },
  {
    "name": "qr-code",
    "link": "qr-code.html"
  },
  {
    "name": "quorum",
    "link": "quorum.html"
  },
  {
    "name": "rarible",
    "link": "rarible.html"
  },
  {
    "name": "receive",
    "link": "receive.html"
  },
  {
    "name": "reject",
    "link": "reject.html"
  },
  {
    "name": "relayer",
    "link": "relayer.html"
  },
  {
    "name": "remote-procedure-call-(rpc)",
    "link": "remote-procedure-call-(rpc).html"
  },
  {
    "name": "remote-procedure-call",
    "link": "remote-procedure-call.html"
  },
  {
    "name": "remove",
    "link": "remove.html"
  },
  {
    "name": "request-(noun)",
    "link": "request-(noun).html"
  },
  {
    "name": "request-(verb)",
    "link": "request-(verb).html"
  },
  {
    "name": "reset",
    "link": "reset.html"
  },
  {
    "name": "restore",
    "link": "restore.html"
  },
  {
    "name": "reveal",
    "link": "reveal.html"
  },
  {
    "name": "rinkeby",
    "link": "rinkeby.html"
  },
  {
    "name": "roadmap",
    "link": "roadmap.html"
  },
  {
    "name": "rocket-pool",
    "link": "rocket-pool.html"
  },
  {
    "name": "rollups",
    "link": "rollups.html"
  },
  {
    "name": "ropsten",
    "link": "ropsten.html"
  },
  {
    "name": "rpc",
    "link": "rpc.html"
  },
  {
    "name": "rug-pull",
    "link": "rug-pull.html"
  },
  {
    "name": "safeheron",
    "link": "safeheron.html"
  },
  {
    "name": "samsung-pay",
    "link": "samsung-pay.html"
  },
  {
    "name": "sandbox",
    "link": "sandbox.html"
  },
  {
    "name": "sardine",
    "link": "sardine.html"
  },
  {
    "name": "satoshi-nakamoto",
    "link": "satoshi-nakamoto.html"
  },
  {
    "name": "save",
    "link": "save.html"
  },
  {
    "name": "scalability",
    "link": "scalability.html"
  },
  {
    "name": "scaling",
    "link": "scaling.html"
  },
  {
    "name": "scam",
    "link": "scam.html"
  },
  {
    "name": "scan",
    "link": "scan.html"
  },
  {
    "name": "scrypt",
    "link": "scrypt.html"
  },
  {
    "name": "sdk",
    "link": "sdk.html"
  },
  {
    "name": "search-engine",
    "link": "search-engine.html"
  },
  {
    "name": "search",
    "link": "search.html"
  },
  {
    "name": "secret-recovery-phrase",
    "link": "secret-recovery-phrase.html"
  },
  {
    "name": "security-&-privacy",
    "link": "security-&-privacy.html"
  },
  {
    "name": "security-token-offering-(sto)",
    "link": "security-token-offering-(sto).html"
  },
  {
    "name": "security-token",
    "link": "security-token.html"
  },
  {
    "name": "seed-phrase",
    "link": "seed-phrase.html"
  },
  {
    "name": "self-custody-(noun)",
    "link": "self-custody-(noun).html"
  },
  {
    "name": "self-executing",
    "link": "self-executing.html"
  },
  {
    "name": "sepolia",
    "link": "sepolia.html"
  },
  {
    "name": "serenity",
    "link": "serenity.html"
  },
  {
    "name": "serialization",
    "link": "serialization.html"
  },
  {
    "name": "settings",
    "link": "settings.html"
  },
  {
    "name": "shard-chain",
    "link": "shard-chain.html"
  },
  {
    "name": "sharding-(noun)",
    "link": "sharding-(noun).html"
  },
  {
    "name": "shielded-transaction",
    "link": "shielded-transaction.html"
  },
  {
    "name": "show",
    "link": "show.html"
  },
  {
    "name": "sidechain",
    "link": "sidechain.html"
  },
  {
    "name": "sign-in",
    "link": "sign-in.html"
  },
  {
    "name": "sign",
    "link": "sign.html"
  },
  {
    "name": "signature-(cryptographic)",
    "link": "signature-(cryptographic).html"
  },
  {
    "name": "skip",
    "link": "skip.html"
  },
  {
    "name": "slashing-condition",
    "link": "slashing-condition.html"
  },
  {
    "name": "slippage",
    "link": "slippage.html"
  },
  {
    "name": "slot",
    "link": "slot.html"
  },
  {
    "name": "smart-contract",
    "link": "smart-contract.html"
  },
  {
    "name": "snap",
    "link": "snap.html"
  },
  {
    "name": "snaps-(metamask-snaps)",
    "link": "snaps-(metamask-snaps).html"
  },
  {
    "name": "soft-fork",
    "link": "soft-fork.html"
  },
  {
    "name": "software-development-kit-(sdk)",
    "link": "software-development-kit-(sdk).html"
  },
  {
    "name": "solidity",
    "link": "solidity.html"
  },
  {
    "name": "source-(noun)",
    "link": "source-(noun).html"
  },
  {
    "name": "speed-up",
    "link": "speed-up.html"
  },
  {
    "name": "stablecoin",
    "link": "stablecoin.html"
  },
  {
    "name": "staking-(noun)",
    "link": "staking-(noun).html"
  },
  {
    "name": "state-channels",
    "link": "state-channels.html"
  },
  {
    "name": "state-logs",
    "link": "state-logs.html"
  },
  {
    "name": "state",
    "link": "state.html"
  },
  {
    "name": "status",
    "link": "status.html"
  },
  {
    "name": "streaming",
    "link": "streaming.html"
  },
  {
    "name": "submit",
    "link": "submit.html"
  },
  {
    "name": "support-center",
    "link": "support-center.html"
  },
  {
    "name": "support",
    "link": "support.html"
  },
  {
    "name": "swap-(noun)",
    "link": "swap-(noun).html"
  },
  {
    "name": "swap-(verb)",
    "link": "swap-(verb).html"
  },
  {
    "name": "switch-(verb)",
    "link": "switch-(verb).html"
  },
  {
    "name": "symbol",
    "link": "symbol.html"
  },
  {
    "name": "szabo",
    "link": "szabo.html"
  },
  {
    "name": "teku",
    "link": "teku.html"
  },
  {
    "name": "testnet-(test-network)",
    "link": "testnet-(test-network).html"
  },
  {
    "name": "testnet-kovan",
    "link": "testnet-kovan.html"
  },
  {
    "name": "testnet-rinkeby",
    "link": "testnet-rinkeby.html"
  },
  {
    "name": "testnet-ropsten",
    "link": "testnet-ropsten.html"
  },
  {
    "name": "testnet",
    "link": "testnet.html"
  },
  {
    "name": "theme",
    "link": "theme.html"
  },
  {
    "name": "tips",
    "link": "tips.html"
  },
  {
    "name": "token-id",
    "link": "token-id.html"
  },
  {
    "name": "token-lockup",
    "link": "token-lockup.html"
  },
  {
    "name": "token-standard",
    "link": "token-standard.html"
  },
  {
    "name": "token",
    "link": "token.html"
  },
  {
    "name": "total-value-locked-(tvl)",
    "link": "total-value-locked-(tvl).html"
  },
  {
    "name": "transaction-block",
    "link": "transaction-block.html"
  },
  {
    "name": "transaction-fee",
    "link": "transaction-fee.html"
  },
  {
    "name": "transaction-id",
    "link": "transaction-id.html"
  },
  {
    "name": "transaction-pool",
    "link": "transaction-pool.html"
  },
  {
    "name": "transaction",
    "link": "transaction.html"
  },
  {
    "name": "transak",
    "link": "transak.html"
  },
  {
    "name": "transfer-(verb)",
    "link": "transfer-(verb).html"
  },
  {
    "name": "trezor",
    "link": "trezor.html"
  },
  {
    "name": "truffle",
    "link": "truffle.html"
  },
  {
    "name": "trustless",
    "link": "trustless.html"
  },
  {
    "name": "turing-complete",
    "link": "turing-complete.html"
  },
  {
    "name": "tutorial",
    "link": "tutorial.html"
  },
  {
    "name": "two-factor-authentication-(2fa)",
    "link": "two-factor-authentication-(2fa).html"
  },
  {
    "name": "txid",
    "link": "txid.html"
  },
  {
    "name": "u2f",
    "link": "u2f.html"
  },
  {
    "name": "uniswap",
    "link": "uniswap.html"
  },
  {
    "name": "unknown",
    "link": "unknown.html"
  },
  {
    "name": "unlock",
    "link": "unlock.html"
  },
  {
    "name": "unspent-transaction-output-(utxo)",
    "link": "unspent-transaction-output-(utxo).html"
  },
  {
    "name": "unspent-transaction-output",
    "link": "unspent-transaction-output.html"
  },
  {
    "name": "update-(verb)",
    "link": "update-(verb).html"
  },
  {
    "name": "upgrade",
    "link": "upgrade.html"
  },
  {
    "name": "url",
    "link": "url.html"
  },
  {
    "name": "usd",
    "link": "usd.html"
  },
  {
    "name": "utxo",
    "link": "utxo.html"
  },
  {
    "name": "validator",
    "link": "validator.html"
  },
  {
    "name": "validity-proof",
    "link": "validity-proof.html"
  },
  {
    "name": "validium",
    "link": "validium.html"
  },
  {
    "name": "vault-decryptor",
    "link": "vault-decryptor.html"
  },
  {
    "name": "vesting",
    "link": "vesting.html"
  },
  {
    "name": "wallet",
    "link": "wallet.html"
  },
  {
    "name": "walletconnect",
    "link": "walletconnect.html"
  },
  {
    "name": "web-3.0",
    "link": "web-3.0.html"
  },
  {
    "name": "web3,-web-3.0",
    "link": "web3,-web-3.0.html"
  },
  {
    "name": "web3",
    "link": "web3.html"
  },
  {
    "name": "webhid",
    "link": "webhid.html"
  },
  {
    "name": "websocket",
    "link": "websocket.html"
  },
  {
    "name": "wei",
    "link": "wei.html"
  },
  {
    "name": "whitepaper",
    "link": "whitepaper.html"
  },
  {
    "name": "wrapping",
    "link": "wrapping.html"
  },
  {
    "name": "wyre",
    "link": "wyre.html"
  },
  {
    "name": "yield-bearing-tokens",
    "link": "yield-bearing-tokens.html"
  },
  {
    "name": "yield-farming",
    "link": "yield-farming.html"
  },
  {
    "name": "zero-address",
    "link": "zero-address.html"
  },
  {
    "name": "zero-knowledge-proof",
    "link": "zero-knowledge-proof.html"
  },
  {
    "name": "zero-knowledge-rollup",
    "link": "zero-knowledge-rollup.html"
  },
  {
    "name": "zk-snarks",
    "link": "zk-snarks.html"
  }
]